bitcode/__init__.py
bitcode/bitcode.py
test_bitcode_alt-1.0.1.dist-info/AUTHORS.rst
test_bitcode_alt-1.0.1.dist-info/CHANGELOG.rst
test_bitcode_alt-1.0.1.dist-info/CODE_OF_CONDUCT.rst
test_bitcode_alt-1.0.1.dist-info/METADATA
test_bitcode_alt-1.0.1.dist-info/NOTICE
test_bitcode_alt-1.0.1.dist-info/WHEEL
test_bitcode_alt-1.0.1.dist-info/apache-2.0.LICENSE
test_bitcode_alt-1.0.1.dist-info/top_level.txt
test_bitcode_alt-1.0.1.dist-info/RECORD
