Metadata-Version: 2.1
Name: test-bitcode-alt
Version: 1.0.1
Summary: bitcode is a fallback pure Python library for intbitset.
Home-page: https://github.com/nexB/bitcode
Author: nexB. Inc. and others
Author-email: info@aboutcode.org
License: Apache-2.0
Keywords: utilities
Classifier: Development Status :: 5 - Production/Stable
Classifier: Intended Audience :: Developers
Classifier: Programming Language :: Python :: 3
Classifier: Programming Language :: Python :: 3 :: Only
Classifier: Programming Language :: Python :: 3.6
Classifier: Programming Language :: Python :: 3.7
Classifier: Programming Language :: Python :: 3.8
Classifier: Programming Language :: Python :: 3.9
Classifier: Programming Language :: Python :: 3.10
Classifier: Topic :: Software Development
Classifier: Topic :: Utilities
Requires-Python: >=3.7
License-File: apache-2.0.LICENSE
License-File: NOTICE
License-File: AUTHORS.rst
License-File: CHANGELOG.rst
License-File: CODE_OF_CONDUCT.rst
Provides-Extra: docs
Requires-Dist: Sphinx (==5.1.0) ; extra == 'docs'
Requires-Dist: sphinx-rtd-theme (>=0.5.0) ; extra == 'docs'
Requires-Dist: doc8 (>=0.8.1) ; extra == 'docs'
Provides-Extra: testing
Requires-Dist: pytest (!=7.0.0,>=6) ; extra == 'testing'
Requires-Dist: pytest-xdist (>=2) ; extra == 'testing'
Requires-Dist: aboutcode-toolkit (>=7.0.2) ; extra == 'testing'
Requires-Dist: pycodestyle (>=2.8.0) ; extra == 'testing'
Requires-Dist: twine ; extra == 'testing'
Requires-Dist: black ; extra == 'testing'
Requires-Dist: isort ; extra == 'testing'
